MANIFEST.in
README.rst
setup.py
aliyun_python_sdk_rds_test.egg-info/PKG-INFO
aliyun_python_sdk_rds_test.egg-info/SOURCES.txt
aliyun_python_sdk_rds_test.egg-info/dependency_links.txt
aliyun_python_sdk_rds_test.egg-info/requires.txt
aliyun_python_sdk_rds_test.egg-info/top_level.txt
aliyunsdkrds/__init__.py
aliyunsdkrds/request/__init__.py
aliyunsdkrds/request/v20120615/DescribeDBInstanceClassListRequest.py
aliyunsdkrds/request/v20120615/__init__.py
aliyunsdkrds/request/v20130528/CreateAccountRequest.py
aliyunsdkrds/request/v20130528/CreateBackupRequest.py
aliyunsdkrds/request/v20130528/CreateChildDBInstanceRequest.py
aliyunsdkrds/request/v20130528/CreateDBInstanceRequest.py
aliyunsdkrds/request/v20130528/CreateDatabaseRequest.py
aliyunsdkrds/request/v20130528/CreateGuardDBInstanceRequest.py
aliyunsdkrds/request/v20130528/CreateImportDataUploadRequest.py
aliyunsdkrds/request/v20130528/DeleteAccountRequest.py
aliyunsdkrds/request/v20130528/DeleteChildInstanceRequest.py
aliyunsdkrds/request/v20130528/DeleteDBInstanceRequest.py
aliyunsdkrds/request/v20130528/DeleteDatabaseRequest.py
aliyunsdkrds/request/v20130528/DescribeAccountsRequest.py
aliyunsdkrds/request/v20130528/DescribeBackupsRequest.py
aliyunsdkrds/request/v20130528/DescribeBinlogFilesRequest.py
aliyunsdkrds/request/v20130528/DescribeDBInstanceClassesRequest.py
aliyunsdkrds/request/v20130528/DescribeDBInstancePerformanceRequest.py
aliyunsdkrds/request/v20130528/DescribeDBInstancesRequest.py
aliyunsdkrds/request/v20130528/DescribeDataFilesRequest.py
aliyunsdkrds/request/v20130528/DescribeDatabasesRequest.py
aliyunsdkrds/request/v20130528/DescribeErrorLogsRequest.py
aliyunsdkrds/request/v20130528/DescribeParameterTemplatesRequest.py
aliyunsdkrds/request/v20130528/DescribeParametersRequest.py
aliyunsdkrds/request/v20130528/DescribeResourceUsageRequest.py
aliyunsdkrds/request/v20130528/DescribeSQLLogRecordsRequest.py
aliyunsdkrds/request/v20130528/DescribeSQLLogReportsRequest.py
aliyunsdkrds/request/v20130528/DescribeSecurityIpsRequest.py
aliyunsdkrds/request/v20130528/DescribeSlowLogRecordsRequest.py
aliyunsdkrds/request/v20130528/DescribeSlowLogsRequest.py
aliyunsdkrds/request/v20130528/DescribeSwitchDBInstanceListRequest.py
